label_converter/__init__.py
label_converter/label_converter.py
tests/__init__.py
tests/test.py
label_converter-0.15.dist-info/LICENSE.md
label_converter-0.15.dist-info/METADATA
label_converter-0.15.dist-info/WHEEL
label_converter-0.15.dist-info/top_level.txt
label_converter-0.15.dist-info/RECORD
