Metadata-Version: 2.1
Name: label_converter
Version: 0.15
Summary: HTML to label png converter
Home-page: https://github.com/finnishnetsolutions/label-converter
Author: Miika Launiainen
Author-email: miika.launiainen@fns.fi
License: UNKNOWN
Platform: UNKNOWN
Classifier: Programming Language :: Python :: 3
Classifier: License :: OSI Approved :: MIT License
Classifier: Operating System :: OS Independent
License-File: LICENSE.md
